s1_enumerator/__init__.py
s1_enumerator/cmr.py
s1_enumerator/constants.py
s1_enumerator/enum.py
s1_enumerator/formatter.py
s1_enumerator/gis.py
s1_enumerator/stack.py
s1_enumerator-0.1.0.dist-info/LICENSE.txt
s1_enumerator-0.1.0.dist-info/METADATA
s1_enumerator-0.1.0.dist-info/WHEEL
s1_enumerator-0.1.0.dist-info/top_level.txt
s1_enumerator-0.1.0.dist-info/RECORD
