Metadata-Version: 2.1
Name: s1-enumerator
Version: 0.1.0
Summary: Enumerates Sentinel-1 A/B Interferograms
Home-page: https://github.com/ACCESS-Cloud-Based-InSAR/s1-enumerator
Author: ACCESS Team
Author-email: charlie.z.marshak@jpl.nasa.gov
License: Apache 2.0
Platform: UNKNOWN
Classifier: Intended Audience :: Science/Research
Classifier: License :: OSI Approved :: BSD License
Classifier: Natural Language :: English
Classifier: Programming Language :: Python :: 3
Classifier: Programming Language :: Python :: 3.8
Classifier: Programming Language :: Python :: 3.9
Requires-Python: ~=3.8
License-File: LICENSE.txt
Requires-Dist: geopandas
Requires-Dist: rasterio
Requires-Dist: asf-search
Requires-Dist: tqdm
Requires-Dist: requests
Provides-Extra: develop
Requires-Dist: flake8 ; extra == 'develop'
Requires-Dist: flake8-import-order ; extra == 'develop'
Requires-Dist: flake8-blind-except ; extra == 'develop'
Requires-Dist: flake8-builtins ; extra == 'develop'
Requires-Dist: pytest ; extra == 'develop'
Requires-Dist: pytest-cov ; extra == 'develop'
